{"cameraMode":{"drawMode":0,"name":"Shaded","section":"Shading Mode"},"sceneLighting":true,"audioPlay":false,"sceneViewState":{"showFog":true,"showMaterialUpdate":false,"showSkybox":true,"showFlares":true,"showImageEffects":true,"showParticleSystems":true},"in2DMode":false,"pivot":{"x":0.5421109199523926,"y":-3.93234920501709,"z":8.549196243286133},"rotation":{"x":0.000909955648239702,"y":0.028191715478897096,"z":-0.00002128332926076837,"w":0.999618411064148},"size":16.745874404907228,"orthographic":false}